odoo/addons/datev_export/README.rst
odoo/addons/datev_export/__init__.py
odoo/addons/datev_export/__manifest__.py
odoo/addons/datev_export/i18n/datev_export.pot
odoo/addons/datev_export/models/__init__.py
odoo/addons/datev_export/models/res_company.py
odoo/addons/datev_export/models/res_config_settings.py
odoo/addons/datev_export/readme/CONFIGURATION.rst
odoo/addons/datev_export/readme/CONTRIBUTORS.md
odoo/addons/datev_export/readme/DESCRIPTION.md
odoo/addons/datev_export/static/description/icon.png
odoo/addons/datev_export/static/description/index.html
odoo/addons/datev_export/tests/__init__.py
odoo/addons/datev_export/tests/test_datev_export.py
odoo/addons/datev_export/views/res_config_settings_views.xml
odoo_addon_datev_export-18.0.1.0.1.dist-info/METADATA
odoo_addon_datev_export-18.0.1.0.1.dist-info/WHEEL
odoo_addon_datev_export-18.0.1.0.1.dist-info/top_level.txt
odoo_addon_datev_export-18.0.1.0.1.dist-info/RECORD
